[
  {
    "category": "ASTROMECHS & PILOTING DROIDS",
    "model": "Astromech Droid",
    "npc": "Rival",
    "brawn": 1,
    "agility": 1,
    "intellect": 2,
    "cunning": 2,
    "willpower": 1,
    "presence": 1,
    "soak": 3,
    "woundThreshold": 11,
    "strainThreshold": 0,
    "meleeDefense": 0,
    "rangedDefense": 0,
    "skills": "Astrogation, Computers, Cool, Mechanics, Piloting (Space)",
    "restricted": false,
    "price": "8250",
    "rarity": "3",
    "sourceURL": "https://star-wars-rpg-ffg.fandom.com/wiki/Astromech_Droid",
    "sourceAPIURL": "https://star-wars-rpg-ffg.fandom.com/api.php?action=parse&page=Astromech_Droid&format=json"
  },
  {
    "category": "ASTROMECHS & PILOTING DROIDS",
    "model": "JC Series Pilot Droid",
    "npc": "Rival",
    "brawn": 1,
    "agility": 3,
    "intellect": 2,
    "cunning": 1,
    "willpower": 1,
    "presence": 1,
    "soak": 2,
    "woundThreshold": 5,
    "strainThreshold": 0,
    "meleeDefense": 0,
    "rangedDefense": 0,
    "skills": "Cool, Piloting (Planetary), Piloting (Space), Ranged (Light)",
    "restricted": false,
    "price": "15000",
    "rarity": "7",
    "sourceURL": "https://star-wars-rpg-ffg.fandom.com/wiki/Industrial_Automaton_JC_Series_Pilot_Droid",
    "sourceAPIURL": "https://star-wars-rpg-ffg.fandom.com/api.php?action=parse&page=Industrial_Automaton_JC_Series_Pilot_Droid&format=json"
  },
  {
    "category": "ASTROMECHS & PILOTING DROIDS",
    "model": "Q7-series Astromech Droid",
    "npc": "Rival",
    "brawn": 1,
    "agility": 2,
    "intellect": 2,
    "cunning": 2,
    "willpower": 1,
    "presence": 1,
    "soak": 2,
    "woundThreshold": 9,
    "strainThreshold": 0,
    "meleeDefense": 0,
    "rangedDefense": 0,
    "skills": "Astrogation, Computers, Cool, Mechanics, Piloting (Space)",
    "restricted": false,
    "price": "6500",
    "rarity": "8",
    "sourceURL": "https://star-wars-rpg-ffg.fandom.com/wiki/Q7-series_Astromech_Droid",
    "sourceAPIURL": "https://star-wars-rpg-ffg.fandom.com/api.php?action=parse&page=Q7-series_Astromech_Droid&format=json"
  },
  {
    "category": "ASTROMECHS & PILOTING DROIDS",
    "model": "R7-series Astromech Droid",
    "npc": "Rival",
    "brawn": 1,
    "agility": 1,
    "intellect": 2,
    "cunning": 2,
    "willpower": 1,
    "presence": 1,
    "soak": 3,
    "woundThreshold": 11,
    "strainThreshold": 0,
    "meleeDefense": 0,
    "rangedDefense": 0,
    "skills": "Astrogation, Computers, Cool, Mechanics, Piloting (Space)",
    "restricted": false,
    "price": "11000",
    "rarity": "6",
    "sourceURL": "https://star-wars-rpg-ffg.fandom.com/wiki/R7-series_Astromech_Droid",
    "sourceAPIURL": "https://star-wars-rpg-ffg.fandom.com/api.php?action=parse&page=R7-series_Astromech_Droid&format=json"
  },
  {
    "category": "ANALYSIS DROIDS",
    "model": "Analysis Droid",
    "npc": "Minion",
    "brawn": 1,
    "agility": 1,
    "intellect": 4,
    "cunning": 1,
    "willpower": 1,
    "presence": 1,
    "soak": 3,
    "woundThreshold": 3,
    "strainThreshold": 0,
    "meleeDefense": 0,
    "rangedDefense": 0,
    "skills": "Computers, Education",
    "restricted": false,
    "price": "7500",
    "rarity": "5",
    "sourceURL": "https://star-wars-rpg-ffg.fandom.com/wiki/Analysis_Droid",
    "sourceAPIURL": "https://star-wars-rpg-ffg.fandom.com/api.php?action=parse&page=Analysis_Droid&format=json"
  },
  {
    "category": "ANALYSIS DROIDS",
    "model": "Interrogation Droid",
    "npc": "Rival",
    "brawn": 1,
    "agility": 1,
    "intellect": 3,
    "cunning": 1,
    "willpower": 2,
    "presence": 1,
    "soak": 3,
    "woundThreshold": 12,
    "strainThreshold": 0,
    "meleeDefense": 0,
    "rangedDefense": 0,
    "skills": "Coercion, Medicine, Perception, Ranged (Light)",
    "restricted": true,
    "price": "9600",
    "rarity": "8",
    "sourceURL": "https://star-wars-rpg-ffg.fandom.com/wiki/Interrogation_Droid",
    "sourceAPIURL": "https://star-wars-rpg-ffg.fandom.com/api.php?action=parse&page=Interrogation_Droid&format=json"
  },
  {
    "category": "ANALYSIS DROIDS",
    "model": "LSx-series Slicer Droid",
    "npc": "Rival",
    "brawn": 1,
    "agility": 2,
    "intellect": 4,
    "cunning": 3,
    "willpower": 2,
    "presence": 2,
    "soak": 3,
    "woundThreshold": 10,
    "strainThreshold": 0,
    "meleeDefense": 0,
    "rangedDefense": 0,
    "skills": "Computers, Cool, Deception, Discipline, Mechanics, Perception, Skulduggery, Stealth",
    "restricted": true,
    "price": "19000",
    "rarity": "8",
    "sourceURL": "https://star-wars-rpg-ffg.fandom.com/wiki/LSx-series_Slicer_Droid",
    "sourceAPIURL": "https://star-wars-rpg-ffg.fandom.com/api.php?action=parse&page=LSx-series_Slicer_Droid&format=json"
  },
  {
    "category": "ANALYSIS DROIDS",
    "model": "RH-Series Research Droid",
    "npc": "Rival",
    "brawn": 1,
    "agility": 1,
    "intellect": 3,
    "cunning": 2,
    "willpower": 1,
    "presence": 1,
    "soak": 2,
    "woundThreshold": 10,
    "strainThreshold": 0,
    "meleeDefense": 0,
    "rangedDefense": 0,
    "skills": "Computers, Core Worlds, Education, Lore, Xenology",
    "restricted": false,
    "price": "11000",
    "rarity": "8",
    "sourceURL": "https://star-wars-rpg-ffg.fandom.com/wiki/RH-Series_Research_Droid",
    "sourceAPIURL": "https://star-wars-rpg-ffg.fandom.com/api.php?action=parse&page=RH-Series_Research_Droid&format=json"
  },
  {
    "category": "ANALYSIS DROIDS",
    "model": "T-Series Tactical Droid",
    "npc": "Rival",
    "brawn": 1,
    "agility": 1,
    "intellect": 3,
    "cunning": 2,
    "willpower": 2,
    "presence": 3,
    "soak": 3,
    "woundThreshold": 10,
    "strainThreshold": 0,
    "meleeDefense": 0,
    "rangedDefense": 0,
    "skills": "Cool, Discipline, Leadership, Perception, Vigilance, Warfare",
    "restricted": true,
    "price": "8000",
    "rarity": "8",
    "sourceURL": "https://star-wars-rpg-ffg.fandom.com/wiki/T-Series_Tactical_Droid",
    "sourceAPIURL": "https://star-wars-rpg-ffg.fandom.com/api.php?action=parse&page=T-Series_Tactical_Droid&format=json"
  },
  {
    "category": "ANALYSIS DROIDS",
    "model": "TS-series Interrogation Droid",
    "npc": "Rival",
    "brawn": 2,
    "agility": 3,
    "intellect": 4,
    "cunning": 4,
    "willpower": 3,
    "presence": 2,
    "soak": 4,
    "woundThreshold": 12,
    "strainThreshold": 0,
    "meleeDefense": 0,
    "rangedDefense": 0,
    "skills": "Coercion, Education, Mechanics, Medicine, Perception, Skulduggery, Xenology",
    "restricted": true,
    "price": "58000",
    "rarity": "9",
    "sourceURL": "https://star-wars-rpg-ffg.fandom.com/wiki/TS-series_Interrogation_Droid",
    "sourceAPIURL": "https://star-wars-rpg-ffg.fandom.com/api.php?action=parse&page=TS-series_Interrogation_Droid&format=json"
  },
  {
    "category": "COMBAT DROIDS",
    "model": "AC Law Enforcement Droid",
    "npc": "Rival",
    "brawn": 3,
    "agility": 1,
    "intellect": 2,
    "cunning": 2,
    "willpower": 1,
    "presence": 1,
    "soak": 5,
    "woundThreshold": 14,
    "strainThreshold": 0,
    "meleeDefense": 2,
    "rangedDefense": 2,
    "skills": "Coercion, Discipline, Melee, Piloting (Planetary), Streetwise, Vigilance",
    "restricted": true,
    "price": "9600",
    "rarity": "5",
    "sourceURL": "https://star-wars-rpg-ffg.fandom.com/wiki/AC_Law_Enforcement_Droid",
    "sourceAPIURL": "https://star-wars-rpg-ffg.fandom.com/api.php?action=parse&page=AC_Law_Enforcement_Droid&format=json"
  },
  {
    "category": "COMBAT DROIDS",
    "model": "Antiquated Battle Droid",
    "npc": "Minion",
    "brawn": 2,
    "agility": 2,
    "intellect": 1,
    "cunning": 1,
    "willpower": 1,
    "presence": 1,
    "soak": 4,
    "woundThreshold": 4,
    "strainThreshold": 0,
    "meleeDefense": 0,
    "rangedDefense": 0,
    "skills": "Ranged (Heavy)",
    "restricted": false,
    "price": "6500",
    "rarity": "5",
    "sourceURL": "https://star-wars-rpg-ffg.fandom.com/wiki/Antiquated_Battle_Droid",
    "sourceAPIURL": "https://star-wars-rpg-ffg.fandom.com/api.php?action=parse&page=Antiquated_Battle_Droid&format=json"
  },
  {
    "category": "COMBAT DROIDS",
    "model": "ASP-19 Battle Droid",
    "npc": "Nemesis",
    "brawn": 4,
    "agility": 4,
    "intellect": 2,
    "cunning": 2,
    "willpower": 3,
    "presence": 2,
    "soak": 6,
    "woundThreshold": 16,
    "strainThreshold": 12,
    "meleeDefense": 2,
    "rangedDefense": 0,
    "skills": "Brawl, Coercion, Lightsaber, Melee, Ranged (Heavy), Vigilance",
    "restricted": true,
    "price": "80000",
    "rarity": "9",
    "sourceURL": "https://star-wars-rpg-ffg.fandom.com/wiki/ASP-19_Battle_Droid",
    "sourceAPIURL": "https://star-wars-rpg-ffg.fandom.com/api.php?action=parse&page=ASP-19_Battle_Droid&format=json"
  },
  {
    "category": "COMBAT DROIDS",
    "model": "Assassin Droid",
    "npc": "Nemesis",
    "brawn": 4,
    "agility": 3,
    "intellect": 3,
    "cunning": 3,
    "willpower": 1,
    "presence": 1,
    "soak": 7,
    "woundThreshold": 19,
    "strainThreshold": 10,
    "meleeDefense": 0,
    "rangedDefense": 1,
    "skills": "Coercion, Computers, Gunnery, Mechanics, Ranged (Heavy), Ranged (Light), Piloting (Planetary), Piloting (Space), Vigilance",
    "restricted": true,
    "price": "65000",
    "rarity": "8",
    "sourceURL": "https://star-wars-rpg-ffg.fandom.com/wiki/Assassin_Droid",
    "sourceAPIURL": "https://star-wars-rpg-ffg.fandom.com/api.php?action=parse&page=Assassin_Droid&format=json"
  },
  {
    "category": "COMBAT DROIDS",
    "model": "BL0-Series Non-lethal Combat Droid",
    "npc": "Rival",
    "brawn": 3,
    "agility": 2,
    "intellect": 1,
    "cunning": 1,
    "willpower": 1,
    "presence": 2,
    "soak": 5,
    "woundThreshold": 12,
    "strainThreshold": 0,
    "meleeDefense": 1,
    "rangedDefense": 1,
    "skills": "Brawl, Cool, Coordination, Ranged (Light), Resilience",
    "restricted": false,
    "price": "5000",
    "rarity": "6",
    "sourceURL": "https://star-wars-rpg-ffg.fandom.com/wiki/BL0-Series_Non-lethal_Combat_Droid",
    "sourceAPIURL": "https://star-wars-rpg-ffg.fandom.com/api.php?action=parse&page=BL0-Series_Non-lethal_Combat_Droid&format=json"
  },
  {
    "category": "COMBAT DROIDS",
    "model": "E522 Assassin Droid",
    "npc": "Nemesis",
    "brawn": 5,
    "agility": 4,
    "intellect": 3,
    "cunning": 3,
    "willpower": 3,
    "presence": 2,
    "soak": 5,
    "woundThreshold": 20,
    "strainThreshold": 12,
    "meleeDefense": 0,
    "rangedDefense": 1,
    "skills": "Brawl, Coercion, Computers, Gunnery, Mechanics, Melee, Ranged (Light), Vigilance",
    "restricted": true,
    "price": "61000",
    "rarity": "8",
    "sourceURL": "https://star-wars-rpg-ffg.fandom.com/wiki/E522_Assassin_Droid",
    "sourceAPIURL": "https://star-wars-rpg-ffg.fandom.com/api.php?action=parse&page=E522_Assassin_Droid&format=json"
  },
  {
    "category": "COMBAT DROIDS",
    "model": "Guardian Police Droid",
    "npc": "Rival",
    "brawn": 3,
    "agility": 2,
    "intellect": 2,
    "cunning": 2,
    "willpower": 3,
    "presence": 2,
    "soak": 4,
    "woundThreshold": 10,
    "strainThreshold": 0,
    "meleeDefense": 0,
    "rangedDefense": 0,
    "skills": "Athletics, Melee, Perception, Piloting (Planetary), Ranged (Light), Streetwise, Vigilance",
    "restricted": false,
    "price": "8100",
    "rarity": "6",
    "sourceURL": "https://star-wars-rpg-ffg.fandom.com/wiki/Guardian_Police_Droid",
    "sourceAPIURL": "https://star-wars-rpg-ffg.fandom.com/api.php?action=parse&page=Guardian_Police_Droid&format=json"
  },
  {
    "category": "COMBAT DROIDS",
    "model": "GV/3-series Guardian Droid",
    "npc": "Rival",
    "brawn": 3,
    "agility": 1,
    "intellect": 1,
    "cunning": 2,
    "willpower": 2,
    "presence": 1,
    "soak": 5,
    "woundThreshold": 15,
    "strainThreshold": 0,
    "meleeDefense": 1,
    "rangedDefense": 0,
    "skills": "Brawl, Perception, Ranged (Light), Vigilance",
    "restricted": false,
    "price": "8000",
    "rarity": "7",
    "sourceURL": "https://star-wars-rpg-ffg.fandom.com/wiki/GV/3-series_Guardian_Droid",
    "sourceAPIURL": "https://star-wars-rpg-ffg.fandom.com/api.php?action=parse&page=GV%2F3-series_Guardian_Droid&format=json"
  },
  {
    "category": "COMBAT DROIDS",
    "model": "IG-100 MagnaGuard",
    "npc": "Nemesis",
    "brawn": 4,
    "agility": 4,
    "intellect": 2,
    "cunning": 3,
    "willpower": 1,
    "presence": 1,
    "soak": 8,
    "woundThreshold": 20,
    "strainThreshold": 14,
    "meleeDefense": 1,
    "rangedDefense": 1,
    "skills": "Athletics, Brawl, Coordination, Melee, Perception, Vigilance",
    "restricted": true,
    "price": "90000",
    "rarity": "10",
    "sourceURL": "https://star-wars-rpg-ffg.fandom.com/wiki/IG-100_MagnaGuard",
    "sourceAPIURL": "https://star-wars-rpg-ffg.fandom.com/api.php?action=parse&page=IG-100_MagnaGuard&format=json"
  },
  {
    "category": "COMBAT DROIDS",
    "model": "IG-RM-series Enforcer Droid",
    "npc": "Rival",
    "brawn": 3,
    "agility": 3,
    "intellect": 2,
    "cunning": 2,
    "willpower": 3,
    "presence": 2,
    "soak": 5,
    "woundThreshold": 13,
    "strainThreshold": 0,
    "meleeDefense": 0,
    "rangedDefense": 0,
    "skills": "Brawl, Coercion, Cool, Melee, Perception, Ranged (Heavy), Vigilance",
    "restricted": false,
    "price": "23000",
    "rarity": "6",
    "sourceURL": "https://star-wars-rpg-ffg.fandom.com/wiki/IG-RM-series_Enforcer_Droid",
    "sourceAPIURL": "https://star-wars-rpg-ffg.fandom.com/api.php?action=parse&page=IG-RM-series_Enforcer_Droid&format=json"
  },
  {
    "category": "COMBAT DROIDS",
    "model": "KX-series Enforcer Droid",
    "npc": "Nemesis",
    "brawn": 4,
    "agility": 3,
    "intellect": 3,
    "cunning": 3,
    "willpower": 2,
    "presence": 2,
    "soak": 7,
    "woundThreshold": 15,
    "strainThreshold": 12,
    "meleeDefense": 0,
    "rangedDefense": 0,
    "skills": "Brawl, Coercion, Computers, Cool, Perception, Ranged (Heavy), Ranged (Light), Vigilance",
    "restricted": true,
    "price": "50000",
    "rarity": "8",
    "sourceURL": "https://star-wars-rpg-ffg.fandom.com/wiki/KX-series_Enforcer_Droid",
    "sourceAPIURL": "https://star-wars-rpg-ffg.fandom.com/api.php?action=parse&page=KX-series_Enforcer_Droid&format=json"
  },
  {
    "category": "COMBAT DROIDS",
    "model": "MI-Series Security Droid",
    "npc": "Nemesis",
    "brawn": 4,
    "agility": 2,
    "intellect": 2,
    "cunning": 2,
    "willpower": 3,
    "presence": 1,
    "soak": 5,
    "woundThreshold": 15,
    "strainThreshold": 10,
    "meleeDefense": 0,
    "rangedDefense": 0,
    "skills": "Brawl, Coercion, Perception, Ranged (Heavy), Vigilance",
    "restricted": true,
    "price": "41225",
    "rarity": "7",
    "sourceURL": "https://star-wars-rpg-ffg.fandom.com/wiki/MI-Series_Security_Droid",
    "sourceAPIURL": "https://star-wars-rpg-ffg.fandom.com/api.php?action=parse&page=MI-Series_Security_Droid&format=json"
  },
  {
    "category": "COMBAT DROIDS",
    "model": "RM-series Military Intelligence Droid",
    "npc": "Nemesis",
    "brawn": 4,
    "agility": 3,
    "intellect": 3,
    "cunning": 4,
    "willpower": 4,
    "presence": 2,
    "soak": 8,
    "woundThreshold": 18,
    "strainThreshold": 10,
    "meleeDefense": 0,
    "rangedDefense": 1,
    "skills": "Computers, Cool, Deception, Mechanics, Perception, Ranged (Heavy), Skulduggery, Stealth, Vigilance, Warfare",
    "restricted": true,
    "price": "43000",
    "rarity": "7",
    "sourceURL": "https://star-wars-rpg-ffg.fandom.com/wiki/RM-series_Military_Intelligence_Droid",
    "sourceAPIURL": "https://star-wars-rpg-ffg.fandom.com/api.php?action=parse&page=RM-series_Military_Intelligence_Droid&format=json"
  },
  {
    "category": "COMBAT DROIDS",
    "model": "Security Droid",
    "npc": "Rival",
    "brawn": 2,
    "agility": 2,
    "intellect": 1,
    "cunning": 2,
    "willpower": 1,
    "presence": 1,
    "soak": 5,
    "woundThreshold": 14,
    "strainThreshold": 0,
    "meleeDefense": 0,
    "rangedDefense": 0,
    "skills": "Ranged (Light), Vigilance",
    "restricted": false,
    "price": "9600",
    "rarity": "5",
    "sourceURL": "https://star-wars-rpg-ffg.fandom.com/wiki/Security_Droid",
    "sourceAPIURL": "https://star-wars-rpg-ffg.fandom.com/api.php?action=parse&page=Security_Droid&format=json"
  },
  {
    "category": "COMBAT DROIDS",
    "model": "Stone Guardian",
    "npc": "Rival",
    "brawn": 5,
    "agility": 3,
    "intellect": 1,
    "cunning": 2,
    "willpower": 1,
    "presence": 1,
    "soak": 7,
    "woundThreshold": 10,
    "strainThreshold": 0,
    "meleeDefense": 0,
    "rangedDefense": 0,
    "skills": "Athletics, Brawl, Perception, Vigilance",
    "restricted": false,
    "price": "25000",
    "rarity": "10",
    "sourceURL": "https://star-wars-rpg-ffg.fandom.com/wiki/Stone_Guardian",
    "sourceAPIURL": "https://star-wars-rpg-ffg.fandom.com/api.php?action=parse&page=Stone_Guardian&format=json"
  },
  {
    "category": "COMBAT DROIDS",
    "model": "TRD-2 Sparring Droid",
    "npc": "Rival",
    "brawn": 3,
    "agility": 3,
    "intellect": 2,
    "cunning": 3,
    "willpower": 1,
    "presence": 1,
    "soak": 6,
    "woundThreshold": 15,
    "strainThreshold": 0,
    "meleeDefense": 2,
    "rangedDefense": 0,
    "skills": "Athletics, Brawl, Coordination, Lightsaber, Melee, Ranged (Heavy)",
    "restricted": false,
    "price": "7750",
    "rarity": "6",
    "sourceURL": "https://star-wars-rpg-ffg.fandom.com/wiki/TRD-2_Sparring_Droid",
    "sourceAPIURL": "https://star-wars-rpg-ffg.fandom.com/api.php?action=parse&page=TRD-2_Sparring_Droid&format=json"
  },
  {
    "category": "HUNTING DROIDS",
    "model": "K-9 Series Hunting Droid",
    "npc": "Rival",
    "brawn": 2,
    "agility": 3,
    "intellect": 1,
    "cunning": 3,
    "willpower": 1,
    "presence": 1,
    "soak": 5,
    "woundThreshold": 9,
    "strainThreshold": 0,
    "meleeDefense": 0,
    "rangedDefense": 0,
    "skills": "Brawl, Perception, Stealth, Survival",
    "restricted": false,
    "price": "7500",
    "rarity": "6",
    "sourceURL": "https://star-wars-rpg-ffg.fandom.com/wiki/Cybot_Galactica_K-9_Series_Hunting_Droid",
    "sourceAPIURL": "https://star-wars-rpg-ffg.fandom.com/api.php?action=parse&page=Cybot_Galactica_K-9_Series_Hunting_Droid&format=json"
  },
  {
    "category": "HUNTING DROIDS",
    "model": "DZ-70 Fugitive Tracker Droid",
    "npc": "Rival",
    "brawn": 2,
    "agility": 1,
    "intellect": 1,
    "cunning": 3,
    "willpower": 1,
    "presence": 1,
    "soak": 4,
    "woundThreshold": 12,
    "strainThreshold": 0,
    "meleeDefense": 0,
    "rangedDefense": 0,
    "skills": "Ranged (Light), Stealth, Survival, Vigilance",
    "restricted": true,
    "price": "9800",
    "rarity": "4",
    "sourceURL": "https://star-wars-rpg-ffg.fandom.com/wiki/DZ-70_Fugitive_Tracker_Droid",
    "sourceAPIURL": "https://star-wars-rpg-ffg.fandom.com/api.php?action=parse&page=DZ-70_Fugitive_Tracker_Droid&format=json"
  },
  {
    "category": "HUNTING DROIDS",
    "model": "SBD series Assistance and Rescue Droid",
    "npc": "Rival",
    "brawn": 2,
    "agility": 3,
    "intellect": 2,
    "cunning": 2,
    "willpower": 1,
    "presence": 3,
    "soak": 4,
    "woundThreshold": 14,
    "strainThreshold": 0,
    "meleeDefense": 0,
    "rangedDefense": 0,
    "skills": "Cool, Coordination, Mechanics, Medicine, Perception",
    "restricted": false,
    "price": "7500",
    "rarity": "3",
    "sourceURL": "https://star-wars-rpg-ffg.fandom.com/wiki/SBD_series_Assistance_and_Rescue_Droid",
    "sourceAPIURL": "https://star-wars-rpg-ffg.fandom.com/api.php?action=parse&page=SBD_series_Assistance_and_Rescue_Droid&format=json"
  },
  {
    "category": "HUNTING DROIDS",
    "model": "87-RM Scout Collector",
    "npc": "Rival",
    "brawn": 4,
    "agility": 1,
    "intellect": 2,
    "cunning": 1,
    "willpower": 1,
    "presence": 3,
    "soak": 8,
    "woundThreshold": 20,
    "strainThreshold": 0,
    "meleeDefense": 1,
    "rangedDefense": 1,
    "skills": "Perception, Xenology",
    "restricted": false,
    "price": "6000",
    "rarity": "6",
    "sourceURL": "https://star-wars-rpg-ffg.fandom.com/wiki/SoroSuub_Corporation_87-RM_Scout_Collector_and_Wanderer_Scout_Surveyor#87-RM_SCOUT_COLLECTOR",
    "sourceAPIURL": "https://star-wars-rpg-ffg.fandom.com/api.php?action=parse&page=SoroSuub_Corporation_87-RM_Scout_Collector_and_Wanderer_Scout_Surveyor%2387-RM_SCOUT_COLLECTOR&format=json"
  },
  {
    "category": "HUNTING DROIDS",
    "model": "Wanderer Scout Surveyor",
    "npc": "Rival",
    "brawn": 2,
    "agility": 4,
    "intellect": 1,
    "cunning": 1,
    "willpower": 1,
    "presence": 1,
    "soak": 3,
    "woundThreshold": 10,
    "strainThreshold": 0,
    "meleeDefense": 0,
    "rangedDefense": 0,
    "skills": "Perception, Ranged (Light), Stealth, Survival",
    "restricted": false,
    "price": "2500",
    "rarity": "6",
    "sourceURL": "https://star-wars-rpg-ffg.fandom.com/wiki/SoroSuub_Corporation_87-RM_Scout_Collector_and_Wanderer_Scout_Surveyor#WANDERER_SCOUT_SURVEYOR",
    "sourceAPIURL": "https://star-wars-rpg-ffg.fandom.com/api.php?action=parse&page=SoroSuub_Corporation_87-RM_Scout_Collector_and_Wanderer_Scout_Surveyor%23WANDERER_SCOUT_SURVEYOR&format=json"
  },
  {
    "category": "LABOUR DROIDS",
    "model": "BT-Series Ordnance Droid",
    "npc": "Rival",
    "brawn": 3,
    "agility": 1,
    "intellect": 3,
    "cunning": 1,
    "willpower": 1,
    "presence": 1,
    "soak": 7,
    "woundThreshold": 15,
    "strainThreshold": 0,
    "meleeDefense": 0,
    "rangedDefense": 0,
    "skills": "Gunnery, Mechanics",
    "restricted": true,
    "price": "13500",
    "rarity": "6",
    "sourceURL": "https://star-wars-rpg-ffg.fandom.com/wiki/BT-Series_Ordnance_Droid",
    "sourceAPIURL": "https://star-wars-rpg-ffg.fandom.com/api.php?action=parse&page=BT-Series_Ordnance_Droid&format=json"
  },
  {
    "category": "LABOUR DROIDS",
    "model": "DTS-series Dismantler Droid",
    "npc": "Rival",
    "brawn": 5,
    "agility": 3,
    "intellect": 2,
    "cunning": 2,
    "willpower": 3,
    "presence": 2,
    "soak": 7,
    "woundThreshold": 15,
    "strainThreshold": 0,
    "meleeDefense": 0,
    "rangedDefense": 1,
    "skills": "Computers, Mechanics, Perception, Ranged (Heavy)",
    "restricted": false,
    "price": "40000",
    "rarity": "6",
    "sourceURL": "https://star-wars-rpg-ffg.fandom.com/wiki/DTS-series_Dismantler_Droid",
    "sourceAPIURL": "https://star-wars-rpg-ffg.fandom.com/api.php?action=parse&page=DTS-series_Dismantler_Droid&format=json"
  },
  {
    "category": "LABOUR DROIDS",
    "model": "DUM-Series Pit Droid",
    "npc": "Minion",
    "brawn": 1,
    "agility": 1,
    "intellect": 0,
    "cunning": 0,
    "willpower": 1,
    "presence": 1,
    "soak": 3,
    "woundThreshold": 2,
    "strainThreshold": 0,
    "meleeDefense": 0,
    "rangedDefense": 0,
    "skills": "Computers, Mechanics, Perception",
    "restricted": false,
    "price": "450",
    "rarity": "1",
    "sourceURL": "https://star-wars-rpg-ffg.fandom.com/wiki/DUM-Series_Pit_Droid",
    "sourceAPIURL": "https://star-wars-rpg-ffg.fandom.com/api.php?action=parse&page=DUM-Series_Pit_Droid&format=json"
  },
  {
    "category": "LABOUR DROIDS",
    "model": "EG-6 Power Droid",
    "npc": "Minion",
    "brawn": 1,
    "agility": 1,
    "intellect": 2,
    "cunning": 1,
    "willpower": 2,
    "presence": 1,
    "soak": 4,
    "woundThreshold": 10,
    "strainThreshold": 0,
    "meleeDefense": 0,
    "rangedDefense": 0,
    "skills": "Computers, Mechanics",
    "restricted": false,
    "price": "3800",
    "rarity": "2",
    "sourceURL": "https://star-wars-rpg-ffg.fandom.com/wiki/EG-6_Power_Droid",
    "sourceAPIURL": "https://star-wars-rpg-ffg.fandom.com/api.php?action=parse&page=EG-6_Power_Droid&format=json"
  },
  {
    "category": "LABOUR DROIDS",
    "model": "GT-Series Construction Droid",
    "npc": "Rival",
    "brawn": 3,
    "agility": 2,
    "intellect": 2,
    "cunning": 1,
    "willpower": 2,
    "presence": 1,
    "soak": 4,
    "woundThreshold": 13,
    "strainThreshold": 0,
    "meleeDefense": 0,
    "rangedDefense": 0,
    "skills": "Computers, Mechanics, Perception",
    "restricted": false,
    "price": "17500",
    "rarity": "4",
    "sourceURL": "https://star-wars-rpg-ffg.fandom.com/wiki/GT-Series_Construction_Droid",
    "sourceAPIURL": "https://star-wars-rpg-ffg.fandom.com/api.php?action=parse&page=GT-Series_Construction_Droid&format=json"
  },
  {
    "category": "LABOUR DROIDS",
    "model": "Gyrowheel 1.42.08-Series Recycling Droid",
    "npc": "Minion",
    "brawn": 3,
    "agility": 3,
    "intellect": 0,
    "cunning": 1,
    "willpower": 1,
    "presence": 1,
    "soak": 4,
    "woundThreshold": 4,
    "strainThreshold": 0,
    "meleeDefense": 0,
    "rangedDefense": 0,
    "skills": "Athletics, Coordination",
    "restricted": false,
    "price": "6500",
    "rarity": "4",
    "sourceURL": "https://star-wars-rpg-ffg.fandom.com/wiki/Gyrowheel_1.42.08-Series_Recycling_Droid",
    "sourceAPIURL": "https://star-wars-rpg-ffg.fandom.com/api.php?action=parse&page=Gyrowheel_1.42.08-Series_Recycling_Droid&format=json"
  },
  {
    "category": "LABOUR DROIDS",
    "model": "FD-series Extinguisher Droid",
    "npc": "Minion",
    "brawn": 2,
    "agility": 1,
    "intellect": 1,
    "cunning": 1,
    "willpower": 1,
    "presence": 1,
    "soak": 3,
    "woundThreshold": 2,
    "strainThreshold": 0,
    "meleeDefense": 0,
    "rangedDefense": 0,
    "skills": "Athletics",
    "restricted": false,
    "price": "8000",
    "rarity": "4",
    "sourceURL": "https://star-wars-rpg-ffg.fandom.com/wiki/Industrial_Automaton_FD-series_Extinguisher_Droid",
    "sourceAPIURL": "https://star-wars-rpg-ffg.fandom.com/api.php?action=parse&page=Industrial_Automaton_FD-series_Extinguisher_Droid&format=json"
  },
  {
    "category": "LABOUR DROIDS",
    "model": "M4-series Messenger Droid",
    "npc": "Rival",
    "brawn": 1,
    "agility": 2,
    "intellect": 2,
    "cunning": 3,
    "willpower": 3,
    "presence": 2,
    "soak": 4,
    "woundThreshold": 20,
    "strainThreshold": 0,
    "meleeDefense": 0,
    "rangedDefense": 0,
    "skills": "Cool, Perception, Ranged (Light), Resilience, Skulduggery, Stealth, Vigilance",
    "restricted": false,
    "price": "6500",
    "rarity": "6",
    "sourceURL": "https://star-wars-rpg-ffg.fandom.com/wiki/M4-series_Messenger_Droid",
    "sourceAPIURL": "https://star-wars-rpg-ffg.fandom.com/api.php?action=parse&page=M4-series_Messenger_Droid&format=json"
  },
  {
    "category": "LABOUR DROIDS",
    "model": "Maintenance Droid",
    "npc": "Minion",
    "brawn": 1,
    "agility": 1,
    "intellect": 1,
    "cunning": 1,
    "willpower": 1,
    "presence": 1,
    "soak": 3,
    "woundThreshold": 3,
    "strainThreshold": 0,
    "meleeDefense": 0,
    "rangedDefense": 0,
    "skills": "Mechanics",
    "restricted": false,
    "price": "7500",
    "rarity": "3",
    "sourceURL": "https://star-wars-rpg-ffg.fandom.com/wiki/Maintenance_Droid",
    "sourceAPIURL": "https://star-wars-rpg-ffg.fandom.com/api.php?action=parse&page=Maintenance_Droid&format=json"
  },
  {
    "category": "LABOUR DROIDS",
    "model": "MSE-series Maintenance Droid",
    "npc": "Minion",
    "brawn": 1,
    "agility": 2,
    "intellect": 1,
    "cunning": 1,
    "willpower": 1,
    "presence": 1,
    "soak": 3,
    "woundThreshold": 3,
    "strainThreshold": 0,
    "meleeDefense": 0,
    "rangedDefense": 0,
    "skills": "Computers, Mechanics, Perception",
    "restricted": false,
    "price": "200",
    "rarity": "2",
    "sourceURL": "https://star-wars-rpg-ffg.fandom.com/wiki/MSE-series_Maintenance_Droid",
    "sourceAPIURL": "https://star-wars-rpg-ffg.fandom.com/api.php?action=parse&page=MSE-series_Maintenance_Droid&format=json"
  },
  {
    "category": "LABOUR DROIDS",
    "model": "Q-4 Borer Droid",
    "npc": "Minion",
    "brawn": 1,
    "agility": 2,
    "intellect": 1,
    "cunning": 1,
    "willpower": 1,
    "presence": 1,
    "soak": 2,
    "woundThreshold": 3,
    "strainThreshold": 0,
    "meleeDefense": 0,
    "rangedDefense": 0,
    "skills": "Perception, Ranged (Light)",
    "restricted": false,
    "price": "2000",
    "rarity": "5",
    "sourceURL": "https://star-wars-rpg-ffg.fandom.com/wiki/Q-4_Borer_Droid",
    "sourceAPIURL": "https://star-wars-rpg-ffg.fandom.com/api.php?action=parse&page=Q-4_Borer_Droid&format=json"
  },
  {
    "category": "LABOUR DROIDS",
    "model": "Q-Signal Messenger Drone",
    "npc": "Rival",
    "brawn": 1,
    "agility": 2,
    "intellect": 2,
    "cunning": 2,
    "willpower": 1,
    "presence": 1,
    "soak": 2,
    "woundThreshold": 8,
    "strainThreshold": 0,
    "meleeDefense": 0,
    "rangedDefense": 0,
    "skills": "Astrogation, Perception, Piloting (Space), Stealth",
    "restricted": false,
    "price": "50500",
    "rarity": "6",
    "sourceURL": "https://star-wars-rpg-ffg.fandom.com/wiki/Q-Signal_Messenger_Drone",
    "sourceAPIURL": "https://star-wars-rpg-ffg.fandom.com/api.php?action=parse&page=Q-Signal_Messenger_Drone&format=json"
  },
  {
    "category": "LABOUR DROIDS",
    "model": "J9 Worker Drone",
    "npc": "Rival",
    "brawn": 1,
    "agility": 2,
    "intellect": 3,
    "cunning": 1,
    "willpower": 2,
    "presence": 1,
    "soak": 2,
    "woundThreshold": 11,
    "strainThreshold": 0,
    "meleeDefense": 0,
    "rangedDefense": 0,
    "skills": "Charm, Education, Negotiation, Xenology",
    "restricted": false,
    "price": "7000",
    "rarity": "3",
    "sourceURL": "https://star-wars-rpg-ffg.fandom.com/wiki/Roche_J9_Worker_Drone",
    "sourceAPIURL": "https://star-wars-rpg-ffg.fandom.com/api.php?action=parse&page=Roche_J9_Worker_Drone&format=json"
  },
  {
    "category": "LABOUR DROIDS",
    "model": "Service Patch Remote",
    "npc": "Minion",
    "brawn": 1,
    "agility": 1,
    "intellect": 1,
    "cunning": 1,
    "willpower": 1,
    "presence": 1,
    "soak": 2,
    "woundThreshold": 5,
    "strainThreshold": 0,
    "meleeDefense": 0,
    "rangedDefense": 0,
    "skills": "Computers, Mechanics",
    "restricted": false,
    "price": "900",
    "rarity": "3",
    "sourceURL": "https://star-wars-rpg-ffg.fandom.com/wiki/Service_Patch_Remote",
    "sourceAPIURL": "https://star-wars-rpg-ffg.fandom.com/api.php?action=parse&page=Service_Patch_Remote&format=json"
  },
  {
    "category": "LABOUR DROIDS",
    "model": "G2 Repair Droid",
    "npc": "Rival",
    "brawn": 1,
    "agility": 2,
    "intellect": 2,
    "cunning": 1,
    "willpower": 1,
    "presence": 2,
    "soak": 1,
    "woundThreshold": 6,
    "strainThreshold": 0,
    "meleeDefense": 0,
    "rangedDefense": 0,
    "skills": "Astrogation, Computers, Core Worlds, Mechanics, Outer Rim, Piloting (Space)",
    "restricted": false,
    "price": "6000",
    "rarity": "5",
    "sourceURL": "https://star-wars-rpg-ffg.fandom.com/wiki/SoroSuub_G2_Repair_Droid",
    "sourceAPIURL": "https://star-wars-rpg-ffg.fandom.com/api.php?action=parse&page=SoroSuub_G2_Repair_Droid&format=json"
  },
  {
    "category": "MEDICAL DROIDS",
    "model": "CT-4 Medical Droid",
    "npc": "Rival",
    "brawn": 1,
    "agility": 1,
    "intellect": 3,
    "cunning": 1,
    "willpower": 2,
    "presence": 1,
    "soak": 2,
    "woundThreshold": 8,
    "strainThreshold": 0,
    "meleeDefense": 0,
    "rangedDefense": 0,
    "skills": "Computers, Discipline, Medicine, Perception, Xenology",
    "restricted": false,
    "price": "20000",
    "rarity": "8",
    "sourceURL": "https://star-wars-rpg-ffg.fandom.com/wiki/CT-4_Medical_Droid",
    "sourceAPIURL": "https://star-wars-rpg-ffg.fandom.com/api.php?action=parse&page=CT-4_Medical_Droid&format=json"
  },
  {
    "category": "MEDICAL DROIDS",
    "model": "Medical Droid",
    "npc": "Rival",
    "brawn": 1,
    "agility": 1,
    "intellect": 2,
    "cunning": 1,
    "willpower": 1,
    "presence": 1,
    "soak": 3,
    "woundThreshold": 10,
    "strainThreshold": 0,
    "meleeDefense": 0,
    "rangedDefense": 0,
    "skills": "Discipline, Medicine, Perception",
    "restricted": false,
    "price": "12000",
    "rarity": "4",
    "sourceURL": "https://star-wars-rpg-ffg.fandom.com/wiki/Medical_Droid",
    "sourceAPIURL": "https://star-wars-rpg-ffg.fandom.com/api.php?action=parse&page=Medical_Droid&format=json"
  },
  {
    "category": "MEDICAL DROIDS",
    "model": "Mini-Med",
    "npc": "Minion",
    "brawn": 1,
    "agility": 1,
    "intellect": 1,
    "cunning": 1,
    "willpower": 1,
    "presence": 0,
    "soak": 2,
    "woundThreshold": 1,
    "strainThreshold": 0,
    "meleeDefense": 0,
    "rangedDefense": 0,
    "skills": "",
    "restricted": false,
    "price": "900",
    "rarity": "3",
    "sourceURL": "https://star-wars-rpg-ffg.fandom.com/wiki/Medtech_Mini-Med",
    "sourceAPIURL": "https://star-wars-rpg-ffg.fandom.com/api.php?action=parse&page=Medtech_Mini-Med&format=json"
  },
  {
    "category": "PROTOCOL DROIDS",
    "model": "3PX-Series Protocol Droid",
    "npc": "Rival",
    "brawn": 1,
    "agility": 1,
    "intellect": 3,
    "cunning": 1,
    "willpower": 1,
    "presence": 2,
    "soak": 2,
    "woundThreshold": 10,
    "strainThreshold": 0,
    "meleeDefense": 0,
    "rangedDefense": 0,
    "skills": "Charm, Education, Negotiation, Outer Rim, Xenology",
    "restricted": false,
    "price": "7750",
    "rarity": "4",
    "sourceURL": "https://star-wars-rpg-ffg.fandom.com/wiki/3PX-Series_Protocol_Droid",
    "sourceAPIURL": "https://star-wars-rpg-ffg.fandom.com/api.php?action=parse&page=3PX-Series_Protocol_Droid&format=json"
  },
  {
    "category": "PROTOCOL DROIDS",
    "model": "5YQ-Series Protocol Droid",
    "npc": "Rival",
    "brawn": 1,
    "agility": 1,
    "intellect": 3,
    "cunning": 1,
    "willpower": 1,
    "presence": 2,
    "soak": 2,
    "woundThreshold": 9,
    "strainThreshold": 0,
    "meleeDefense": 0,
    "rangedDefense": 0,
    "skills": "Charm, Core Worlds, Education, Lore, Outer Rim, Underworld, Warfare, Xenology",
    "restricted": false,
    "price": "5500",
    "rarity": "3",
    "sourceURL": "https://star-wars-rpg-ffg.fandom.com/wiki/5YQ-Series_Protocol_Droid",
    "sourceAPIURL": "https://star-wars-rpg-ffg.fandom.com/api.php?action=parse&page=5YQ-Series_Protocol_Droid&format=json"
  },
  {
    "category": "PROTOCOL DROIDS",
    "model": "BD10-Series Assay Support Droid",
    "npc": "Rival",
    "brawn": 1,
    "agility": 1,
    "intellect": 4,
    "cunning": 3,
    "willpower": 1,
    "presence": 3,
    "soak": 3,
    "woundThreshold": 10,
    "strainThreshold": 0,
    "meleeDefense": 0,
    "rangedDefense": 0,
    "skills": "Charm, Negotiation, Outer Rim",
    "restricted": false,
    "price": "8500",
    "rarity": "5",
    "sourceURL": "https://star-wars-rpg-ffg.fandom.com/wiki/BD10-Series_Assay_Support_Droid",
    "sourceAPIURL": "https://star-wars-rpg-ffg.fandom.com/api.php?action=parse&page=BD10-Series_Assay_Support_Droid&format=json"
  },
  {
    "category": "PROTOCOL DROIDS",
    "model": "CZ-Series Communications/Business Droid",
    "npc": "Rival",
    "brawn": 1,
    "agility": 1,
    "intellect": 3,
    "cunning": 2,
    "willpower": 1,
    "presence": 2,
    "soak": 2,
    "woundThreshold": 10,
    "strainThreshold": 0,
    "meleeDefense": 0,
    "rangedDefense": 0,
    "skills": "Core Worlds, Education, Negotiation, Perception",
    "restricted": false,
    "price": "9000",
    "rarity": "4",
    "sourceURL": "https://star-wars-rpg-ffg.fandom.com/wiki/CZ-Series_Communications/Business_Droid",
    "sourceAPIURL": "https://star-wars-rpg-ffg.fandom.com/api.php?action=parse&page=CZ-Series_Communications%2FBusiness_Droid&format=json"
  },
  {
    "category": "PROTOCOL DROIDS",
    "model": "ED-V8-Series Envoy Droid",
    "npc": "Rival",
    "brawn": 1,
    "agility": 1,
    "intellect": 3,
    "cunning": 2,
    "willpower": 1,
    "presence": 1,
    "soak": 3,
    "woundThreshold": 10,
    "strainThreshold": 0,
    "meleeDefense": 0,
    "rangedDefense": 0,
    "skills": "Education, Negotiation, Outer Rim, Perception",
    "restricted": false,
    "price": "8000",
    "rarity": "7",
    "sourceURL": "https://star-wars-rpg-ffg.fandom.com/wiki/ED-V8-Series_Envoy_Droid",
    "sourceAPIURL": "https://star-wars-rpg-ffg.fandom.com/api.php?action=parse&page=ED-V8-Series_Envoy_Droid&format=json"
  },
  {
    "category": "PROTOCOL DROIDS",
    "model": "LOM-Series Protocol Droid",
    "npc": "Rival",
    "brawn": 1,
    "agility": 1,
    "intellect": 3,
    "cunning": 1,
    "willpower": 1,
    "presence": 2,
    "soak": 2,
    "woundThreshold": 10,
    "strainThreshold": 0,
    "meleeDefense": 0,
    "rangedDefense": 0,
    "skills": "Charm, Education, Negotiation, Outer Rim, Xenology",
    "restricted": false,
    "price": "8500",
    "rarity": "5",
    "sourceURL": "https://star-wars-rpg-ffg.fandom.com/wiki/LOM-Series_Protocol_Droid",
    "sourceAPIURL": "https://star-wars-rpg-ffg.fandom.com/api.php?action=parse&page=LOM-Series_Protocol_Droid&format=json"
  },
  {
    "category": "PROTOCOL DROIDS",
    "model": "LRD-Series Envoy Droid",
    "npc": "Rival",
    "brawn": 1,
    "agility": 1,
    "intellect": 2,
    "cunning": 1,
    "willpower": 2,
    "presence": 3,
    "soak": 2,
    "woundThreshold": 10,
    "strainThreshold": 0,
    "meleeDefense": 0,
    "rangedDefense": 0,
    "skills": "Charm, Education, Negotiation, Perception",
    "restricted": false,
    "price": "15000",
    "rarity": "5",
    "sourceURL": "https://star-wars-rpg-ffg.fandom.com/wiki/LRD-Series_Envoy_Droid",
    "sourceAPIURL": "https://star-wars-rpg-ffg.fandom.com/api.php?action=parse&page=LRD-Series_Envoy_Droid&format=json"
  },
  {
    "category": "PROTOCOL DROIDS",
    "model": "M-3PO-Series Military Protocol Droid",
    "npc": "Rival",
    "brawn": 1,
    "agility": 1,
    "intellect": 3,
    "cunning": 1,
    "willpower": 2,
    "presence": 1,
    "soak": 2,
    "woundThreshold": 14,
    "strainThreshold": 0,
    "meleeDefense": 0,
    "rangedDefense": 0,
    "skills": "Discipline, Education, Vigilance, Warfare",
    "restricted": true,
    "price": "12000",
    "rarity": "5",
    "sourceURL": "https://star-wars-rpg-ffg.fandom.com/wiki/M-3PO-Series_Military_Protocol_Droid",
    "sourceAPIURL": "https://star-wars-rpg-ffg.fandom.com/api.php?action=parse&page=M-3PO-Series_Military_Protocol_Droid&format=json"
  },
  {
    "category": "PROTOCOL DROIDS",
    "model": "KLC Series Exchequer Droid",
    "npc": "Rival",
    "brawn": 1,
    "agility": 1,
    "intellect": 3,
    "cunning": 1,
    "willpower": 1,
    "presence": 3,
    "soak": 2,
    "woundThreshold": 8,
    "strainThreshold": 0,
    "meleeDefense": 0,
    "rangedDefense": 0,
    "skills": "Charm, Computers, Cool, Negotiation",
    "restricted": false,
    "price": "10000",
    "rarity": "5",
    "sourceURL": "https://star-wars-rpg-ffg.fandom.com/wiki/MerenData_KLC_Series_Exchequer_Droid",
    "sourceAPIURL": "https://star-wars-rpg-ffg.fandom.com/api.php?action=parse&page=MerenData_KLC_Series_Exchequer_Droid&format=json"
  },
  {
    "category": "PROTOCOL DROIDS",
    "model": "Protocol Droid (FaD)",
    "npc": "Rival",
    "brawn": 1,
    "agility": 1,
    "intellect": 3,
    "cunning": 1,
    "willpower": 1,
    "presence": 2,
    "soak": 3,
    "woundThreshold": 10,
    "strainThreshold": 0,
    "meleeDefense": 0,
    "rangedDefense": 0,
    "skills": "Charm, Education, Negotiation, Perception, Xenology",
    "restricted": false,
    "price": "8000",
    "rarity": "5",
    "sourceURL": "https://star-wars-rpg-ffg.fandom.com/wiki/Protocol_Droid",
    "sourceAPIURL": "https://star-wars-rpg-ffg.fandom.com/api.php?action=parse&page=Protocol_Droid&format=json"
  },
  {
    "category": "PROTOCOL DROIDS",
    "model": "Protocol Droid (AoR, EotE)",
    "npc": "Rival",
    "brawn": 1,
    "agility": 1,
    "intellect": 3,
    "cunning": 1,
    "willpower": 1,
    "presence": 2,
    "soak": 3,
    "woundThreshold": 10,
    "strainThreshold": 0,
    "meleeDefense": 0,
    "rangedDefense": 0,
    "skills": "Charm, Education, Negotiation, Perception, Xenology",
    "restricted": false,
    "price": "8000",
    "rarity": "4",
    "sourceURL": "https://star-wars-rpg-ffg.fandom.com/wiki/Protocol_Droid",
    "sourceAPIURL": "https://star-wars-rpg-ffg.fandom.com/api.php?action=parse&page=Protocol_Droid&format=json"
  },
  {
    "category": "PROTOCOL DROIDS",
    "model": "RA-7 Protocol Droid",
    "npc": "Rival",
    "brawn": 2,
    "agility": 1,
    "intellect": 3,
    "cunning": 3,
    "willpower": 2,
    "presence": 2,
    "soak": 3,
    "woundThreshold": 10,
    "strainThreshold": 0,
    "meleeDefense": 0,
    "rangedDefense": 0,
    "skills": "Deception, Education, Negotiation, Perception, Skulduggery, Stealth, Vigilance, Xenology",
    "restricted": true,
    "price": "12000",
    "rarity": "6",
    "sourceURL": "https://star-wars-rpg-ffg.fandom.com/wiki/RA-7_Protocol_Droid",
    "sourceAPIURL": "https://star-wars-rpg-ffg.fandom.com/api.php?action=parse&page=RA-7_Protocol_Droid&format=json"
  },
  {
    "category": "PROTOCOL DROIDS",
    "model": "Siak-series Protocol Droid",
    "npc": "Rival",
    "brawn": 1,
    "agility": 1,
    "intellect": 3,
    "cunning": 2,
    "willpower": 2,
    "presence": 2,
    "soak": 2,
    "woundThreshold": 10,
    "strainThreshold": 0,
    "meleeDefense": 0,
    "rangedDefense": 0,
    "skills": "Charm, Education, Negotiation, Xenology",
    "restricted": false,
    "price": "10000",
    "rarity": "4",
    "sourceURL": "https://star-wars-rpg-ffg.fandom.com/wiki/Roche_Siak-series_Protocol_Droid",
    "sourceAPIURL": "https://star-wars-rpg-ffg.fandom.com/api.php?action=parse&page=Roche_Siak-series_Protocol_Droid&format=json"
  },
  {
    "category": "PROTOCOL DROIDS",
    "model": "SDMN Series Session Droid",
    "npc": "Rival",
    "brawn": 1,
    "agility": 2,
    "intellect": 2,
    "cunning": 2,
    "willpower": 1,
    "presence": 3,
    "soak": 3,
    "woundThreshold": 7,
    "strainThreshold": 0,
    "meleeDefense": 0,
    "rangedDefense": 0,
    "skills": "Charm, Cool, Computers, Coordination, Deception",
    "restricted": false,
    "price": "4000",
    "rarity": "5",
    "sourceURL": "https://star-wars-rpg-ffg.fandom.com/wiki/SDMN_Series_Session_Droid",
    "sourceAPIURL": "https://star-wars-rpg-ffg.fandom.com/api.php?action=parse&page=SDMN_Series_Session_Droid&format=json"
  },
  {
    "category": "PROTOCOL DROIDS",
    "model": "TC-Series Protocol Droid",
    "npc": "Rival",
    "brawn": 1,
    "agility": 1,
    "intellect": 3,
    "cunning": 1,
    "willpower": 1,
    "presence": 2,
    "soak": 2,
    "woundThreshold": 10,
    "strainThreshold": 0,
    "meleeDefense": 0,
    "rangedDefense": 0,
    "skills": "Charm, Education, Negotiation, Perception, Xenology",
    "restricted": false,
    "price": "10000",
    "rarity": "4",
    "sourceURL": "https://star-wars-rpg-ffg.fandom.com/wiki/TC-Series_Protocol_Droid",
    "sourceAPIURL": "https://star-wars-rpg-ffg.fandom.com/api.php?action=parse&page=TC-Series_Protocol_Droid&format=json"
  },
  {
    "category": "PROTOCOL DROIDS",
    "model": "TTS20-Series Dialectic Droid",
    "npc": "Rival",
    "brawn": 2,
    "agility": 1,
    "intellect": 3,
    "cunning": 2,
    "willpower": 1,
    "presence": 4,
    "soak": 3,
    "woundThreshold": 8,
    "strainThreshold": 0,
    "meleeDefense": 0,
    "rangedDefense": 0,
    "skills": "Charm, Cool, Core Worlds, Deception, Education, Negotiation, Perception, Streetwise",
    "restricted": false,
    "price": "5400",
    "rarity": "7",
    "sourceURL": "https://star-wars-rpg-ffg.fandom.com/wiki/TTS20-Series_Dialectic_Droid",
    "sourceAPIURL": "https://star-wars-rpg-ffg.fandom.com/api.php?action=parse&page=TTS20-Series_Dialectic_Droid&format=json"
  },
  {
    "category": "REMOTES",
    "model": "Butterbug Remote",
    "npc": "Minion",
    "brawn": 1,
    "agility": 1,
    "intellect": 1,
    "cunning": 1,
    "willpower": 1,
    "presence": 1,
    "soak": 2,
    "woundThreshold": 3,
    "strainThreshold": 0,
    "meleeDefense": 0,
    "rangedDefense": 0,
    "skills": "Mechanics, Melee",
    "restricted": false,
    "price": "700",
    "rarity": "4",
    "sourceURL": "https://star-wars-rpg-ffg.fandom.com/wiki/Butterbug_Remote",
    "sourceAPIURL": "https://star-wars-rpg-ffg.fandom.com/api.php?action=parse&page=Butterbug_Remote&format=json"
  },
  {
    "category": "REMOTES",
    "model": "EOD-Mk IV Explosives Disposal Remote",
    "npc": "Minion",
    "brawn": 1,
    "agility": 1,
    "intellect": 1,
    "cunning": 1,
    "willpower": 1,
    "presence": 1,
    "soak": 2,
    "woundThreshold": 2,
    "strainThreshold": 0,
    "meleeDefense": 0,
    "rangedDefense": 0,
    "skills": "Mechanics, Perception, Vigilance",
    "restricted": true,
    "price": "500",
    "rarity": "6",
    "sourceURL": "https://star-wars-rpg-ffg.fandom.com/wiki/EOD-Mk_IV_Explosives_Disposal_Remote",
    "sourceAPIURL": "https://star-wars-rpg-ffg.fandom.com/api.php?action=parse&page=EOD-Mk_IV_Explosives_Disposal_Remote&format=json"
  },
  {
    "category": "REMOTES",
    "model": "Generic Remote",
    "npc": "Minion",
    "brawn": 1,
    "agility": 1,
    "intellect": 1,
    "cunning": 1,
    "willpower": 1,
    "presence": 1,
    "soak": 2,
    "woundThreshold": 5,
    "strainThreshold": 0,
    "meleeDefense": 0,
    "rangedDefense": 0,
    "skills": "Perception",
    "restricted": false,
    "price": "400",
    "rarity": "2",
    "sourceURL": "https://star-wars-rpg-ffg.fandom.com/wiki/Generic_Remote",
    "sourceAPIURL": "https://star-wars-rpg-ffg.fandom.com/api.php?action=parse&page=Generic_Remote&format=json"
  },
  {
    "category": "REMOTES",
    "model": "Marksman-H Combat Remote",
    "npc": "Minion",
    "brawn": 1,
    "agility": 3,
    "intellect": 1,
    "cunning": 1,
    "willpower": 1,
    "presence": 1,
    "soak": 1,
    "woundThreshold": 3,
    "strainThreshold": 0,
    "meleeDefense": 1,
    "rangedDefense": 1,
    "skills": "Perception, Ranged (Light)",
    "restricted": false,
    "price": "350",
    "rarity": "5",
    "sourceURL": "https://star-wars-rpg-ffg.fandom.com/wiki/Marksman-H_Combat_Remote",
    "sourceAPIURL": "https://star-wars-rpg-ffg.fandom.com/api.php?action=parse&page=Marksman-H_Combat_Remote&format=json"
  },
  {
    "category": "REMOTES",
    "model": "P2F Hostile Environment Remote",
    "npc": "Minion",
    "brawn": 1,
    "agility": 2,
    "intellect": 1,
    "cunning": 3,
    "willpower": 1,
    "presence": 1,
    "soak": 2,
    "woundThreshold": 4,
    "strainThreshold": 0,
    "meleeDefense": 0,
    "rangedDefense": 0,
    "skills": "Athletics, Cool, Perception, Resilience",
    "restricted": false,
    "price": "3500",
    "rarity": "4",
    "sourceURL": "https://star-wars-rpg-ffg.fandom.com/wiki/P2F_Hostile_Environment_Remote",
    "sourceAPIURL": "https://star-wars-rpg-ffg.fandom.com/api.php?action=parse&page=P2F_Hostile_Environment_Remote&format=json"
  },
  {
    "category": "REMOTES",
    "model": "Shield Remote",
    "npc": "Minion",
    "brawn": 1,
    "agility": 1,
    "intellect": 1,
    "cunning": 1,
    "willpower": 1,
    "presence": 1,
    "soak": 3,
    "woundThreshold": 6,
    "strainThreshold": 0,
    "meleeDefense": 1,
    "rangedDefense": 1,
    "skills": "Vigilance",
    "restricted": false,
    "price": "1100",
    "rarity": "5",
    "sourceURL": "https://star-wars-rpg-ffg.fandom.com/wiki/Shield_Remote",
    "sourceAPIURL": "https://star-wars-rpg-ffg.fandom.com/api.php?action=parse&page=Shield_Remote&format=json"
  },
  {
    "category": "REMOTES",
    "model": "WSW Mk III \"Harrier\" Combat Remote",
    "npc": "Minion",
    "brawn": 1,
    "agility": 3,
    "intellect": 1,
    "cunning": 1,
    "willpower": 1,
    "presence": 1,
    "soak": 3,
    "woundThreshold": 8,
    "strainThreshold": 0,
    "meleeDefense": 0,
    "rangedDefense": 0,
    "skills": "Perception, Ranged (Heavy), Ranged (Light), Vigilance",
    "restricted": true,
    "price": "6000",
    "rarity": "6",
    "sourceURL": "https://star-wars-rpg-ffg.fandom.com/wiki/WSW_Mk_III_%22Harrier%22_Combat_Remote",
    "sourceAPIURL": "https://star-wars-rpg-ffg.fandom.com/api.php?action=parse&page=WSW_Mk_III_%2522Harrier%2522_Combat_Remote&format=json"
  },
  {
    "category": "SURVEILLANCE DROIDS",
    "model": "AC1-series Surveillance Droid",
    "npc": "Minion",
    "brawn": 1,
    "agility": 2,
    "intellect": 1,
    "cunning": 1,
    "willpower": 1,
    "presence": 1,
    "soak": 2,
    "woundThreshold": 8,
    "strainThreshold": 0,
    "meleeDefense": 0,
    "rangedDefense": 0,
    "skills": "Perception, Ranged (Light), Stealth",
    "restricted": false,
    "price": "1100",
    "rarity": "4",
    "sourceURL": "https://star-wars-rpg-ffg.fandom.com/wiki/AC1-series_Surveillance_Droid",
    "sourceAPIURL": "https://star-wars-rpg-ffg.fandom.com/api.php?action=parse&page=AC1-series_Surveillance_Droid&format=json"
  },
  {
    "category": "SURVEILLANCE DROIDS",
    "model": "Chameleon Droid",
    "npc": "Rival",
    "brawn": 2,
    "agility": 3,
    "intellect": 1,
    "cunning": 2,
    "willpower": 1,
    "presence": 1,
    "soak": 3,
    "woundThreshold": 8,
    "strainThreshold": 0,
    "meleeDefense": 0,
    "rangedDefense": 0,
    "skills": "Perception, Ranged (Heavy), Stealth",
    "restricted": false,
    "price": "4000",
    "rarity": "6",
    "sourceURL": "https://star-wars-rpg-ffg.fandom.com/wiki/Chameleon_Droid",
    "sourceAPIURL": "https://star-wars-rpg-ffg.fandom.com/api.php?action=parse&page=Chameleon_Droid&format=json"
  },
  {
    "category": "SURVEILLANCE DROIDS",
    "model": "All-Terrain Exploration Droid",
    "npc": "Rival",
    "brawn": 1,
    "agility": 3,
    "intellect": 1,
    "cunning": 3,
    "willpower": 1,
    "presence": 1,
    "soak": 4,
    "woundThreshold": 15,
    "strainThreshold": 0,
    "meleeDefense": 0,
    "rangedDefense": 0,
    "skills": "Coordination, Perception, Ranged (Heavy), Vigilance",
    "restricted": false,
    "price": "8900",
    "rarity": "5",
    "sourceURL": "https://star-wars-rpg-ffg.fandom.com/wiki/Cybot_Galactica/KDY_All-Terrain_Exploration_Droid",
    "sourceAPIURL": "https://star-wars-rpg-ffg.fandom.com/api.php?action=parse&page=Cybot_Galactica%2FKDY_All-Terrain_Exploration_Droid&format=json"
  },
  {
    "category": "SURVEILLANCE DROIDS",
    "model": "ID9 Seeker Droid",
    "npc": "Minion",
    "brawn": 1,
    "agility": 3,
    "intellect": 1,
    "cunning": 2,
    "willpower": 1,
    "presence": 1,
    "soak": 3,
    "woundThreshold": 5,
    "strainThreshold": 0,
    "meleeDefense": 0,
    "rangedDefense": 0,
    "skills": "Computers, Coordination, Melee, Stealth",
    "restricted": true,
    "price": "4500",
    "rarity": "7",
    "sourceURL": "https://star-wars-rpg-ffg.fandom.com/wiki/ID9_Seeker_Droid",
    "sourceAPIURL": "https://star-wars-rpg-ffg.fandom.com/api.php?action=parse&page=ID9_Seeker_Droid&format=json"
  },
  {
    "category": "SURVEILLANCE DROIDS",
    "model": "Hologlide J57 Cam Droid",
    "npc": "Minion",
    "brawn": 1,
    "agility": 3,
    "intellect": 1,
    "cunning": 1,
    "willpower": 1,
    "presence": 1,
    "soak": 0,
    "woundThreshold": 2,
    "strainThreshold": 0,
    "meleeDefense": 0,
    "rangedDefense": 0,
    "skills": "Perception, Vigilance",
    "restricted": false,
    "price": "800",
    "rarity": "3",
    "sourceURL": "https://star-wars-rpg-ffg.fandom.com/wiki/Industrial_Automaton_Hologlide_J57_Cam_Droid",
    "sourceAPIURL": "https://star-wars-rpg-ffg.fandom.com/api.php?action=parse&page=Industrial_Automaton_Hologlide_J57_Cam_Droid&format=json"
  },
  {
    "category": "SURVEILLANCE DROIDS",
    "model": "RMD-20 \"Eye in the Sky\"",
    "npc": "Minion",
    "brawn": 1,
    "agility": 3,
    "intellect": 1,
    "cunning": 1,
    "willpower": 1,
    "presence": 1,
    "soak": 1,
    "woundThreshold": 3,
    "strainThreshold": 0,
    "meleeDefense": 0,
    "rangedDefense": 0,
    "skills": "Perception, Vigilance",
    "restricted": false,
    "price": "500",
    "rarity": "4",
    "sourceURL": "https://star-wars-rpg-ffg.fandom.com/wiki/RMD-20_%22Eye_in_the_Sky%22",
    "sourceAPIURL": "https://star-wars-rpg-ffg.fandom.com/api.php?action=parse&page=RMD-20_%2522Eye_in_the_Sky%2522&format=json"
  },
  {
    "category": "SURVEILLANCE DROIDS",
    "model": "SR-series Scout/Observation Droid",
    "npc": "Rival",
    "brawn": 2,
    "agility": 3,
    "intellect": 3,
    "cunning": 3,
    "willpower": 3,
    "presence": 2,
    "soak": 4,
    "woundThreshold": 13,
    "strainThreshold": 0,
    "meleeDefense": 0,
    "rangedDefense": 0,
    "skills": "Athletics, Computers, Perception, Ranged (Heavy), Stealth, Vigilance, Warfare",
    "restricted": true,
    "price": "13000",
    "rarity": "6",
    "sourceURL": "https://star-wars-rpg-ffg.fandom.com/wiki/SR-series_Scout/Observation_Droid",
    "sourceAPIURL": "https://star-wars-rpg-ffg.fandom.com/api.php?action=parse&page=SR-series_Scout%2FObservation_Droid&format=json"
  },
  {
    "category": "SURVEILLANCE DROIDS",
    "model": "TC-SC Infiltration Droid",
    "npc": "Nemesis",
    "brawn": 2,
    "agility": 2,
    "intellect": 3,
    "cunning": 4,
    "willpower": 2,
    "presence": 3,
    "soak": 3,
    "woundThreshold": 10,
    "strainThreshold": 10,
    "meleeDefense": 0,
    "rangedDefense": 0,
    "skills": "Athletics, Computers, Cool, Deception, Melee, Perception, Ranged (Light), Skulduggery, Stealth, Vigilance",
    "restricted": true,
    "price": "15600",
    "rarity": "8",
    "sourceURL": "https://star-wars-rpg-ffg.fandom.com/wiki/TC-SC_Infiltration_Droid",
    "sourceAPIURL": "https://star-wars-rpg-ffg.fandom.com/api.php?action=parse&page=TC-SC_Infiltration_Droid&format=json"
  },
  {
    "category": "SURVEILLANCE DROIDS",
    "model": "Viper Probe Droid",
    "npc": "Rival",
    "brawn": 2,
    "agility": 3,
    "intellect": 2,
    "cunning": 3,
    "willpower": 1,
    "presence": 1,
    "soak": 4,
    "woundThreshold": 12,
    "strainThreshold": 0,
    "meleeDefense": 0,
    "rangedDefense": 1,
    "skills": "Cool, Perception, Ranged (Light), Survival, Vigilance",
    "restricted": true,
    "price": "13700",
    "rarity": "7",
    "sourceURL": "https://star-wars-rpg-ffg.fandom.com/wiki/Viper_Probe_Droid",
    "sourceAPIURL": "https://star-wars-rpg-ffg.fandom.com/api.php?action=parse&page=Viper_Probe_Droid&format=json"
  },
  {
    "category": "STARSHIP & VEHICULAR DROIDS",
    "model": "Droid Tri-Fighter",
    "npc": "3",
    "brawn": 5,
    "agility": 0,
    "intellect": 0,
    "cunning": 0,
    "willpower": 0,
    "presence": 0,
    "soak": 2,
    "woundThreshold": 0,
    "strainThreshold": 2,
    "meleeDefense": 12,
    "rangedDefense": 0,
    "skills": "8",
    "restricted": true,
    "price": "40000",
    "rarity": "8",
    "sourceURL": "https://star-wars-rpg-ffg.fandom.com/wiki/Droid_Tri-Fighter",
    "sourceAPIURL": "https://star-wars-rpg-ffg.fandom.com/api.php?action=parse&page=Droid_Tri-Fighter&format=json"
  },
  {
    "category": "STARSHIP & VEHICULAR DROIDS",
    "model": "HMP Droid Gunship",
    "npc": "3",
    "brawn": 3,
    "agility": 0,
    "intellect": 0,
    "cunning": 0,
    "willpower": 0,
    "presence": 0,
    "soak": 0,
    "woundThreshold": 2,
    "strainThreshold": 4,
    "meleeDefense": 20,
    "rangedDefense": 0,
    "skills": "16",
    "restricted": true,
    "price": "60000",
    "rarity": "8",
    "sourceURL": "https://star-wars-rpg-ffg.fandom.com/wiki/HMP_Droid_Gunship",
    "sourceAPIURL": "https://star-wars-rpg-ffg.fandom.com/api.php?action=parse&page=HMP_Droid_Gunship&format=json"
  },
  {
    "category": "STARSHIP & VEHICULAR DROIDS",
    "model": "Hyena-class Droid Bomber",
    "npc": "3",
    "brawn": 4,
    "agility": 0,
    "intellect": 0,
    "cunning": 0,
    "willpower": 0,
    "presence": 0,
    "soak": 0,
    "woundThreshold": 0,
    "strainThreshold": 3,
    "meleeDefense": 14,
    "rangedDefense": 0,
    "skills": "12",
    "restricted": true,
    "price": "120000",
    "rarity": "7",
    "sourceURL": "https://star-wars-rpg-ffg.fandom.com/wiki/Hyena-class_Droid_Bomber",
    "sourceAPIURL": "https://star-wars-rpg-ffg.fandom.com/api.php?action=parse&page=Hyena-class_Droid_Bomber&format=json"
  },
  {
    "category": "STARSHIP & VEHICULAR DROIDS",
    "model": "I-C2 Civil-Industrial Droid",
    "npc": "4",
    "brawn": 1,
    "agility": 0,
    "intellect": 0,
    "cunning": 0,
    "willpower": 0,
    "presence": 0,
    "soak": -2,
    "woundThreshold": 0,
    "strainThreshold": 3,
    "meleeDefense": 38,
    "rangedDefense": 0,
    "skills": "30",
    "restricted": false,
    "price": "1700000",
    "rarity": "6",
    "sourceURL": "https://star-wars-rpg-ffg.fandom.com/wiki/I-C2_Civil-Industrial_Droid",
    "sourceAPIURL": "https://star-wars-rpg-ffg.fandom.com/api.php?action=parse&page=I-C2_Civil-Industrial_Droid&format=json"
  },
  {
    "category": "STARSHIP & VEHICULAR DROIDS",
    "model": "I-C4a Combat Construction Droid",
    "npc": "3",
    "brawn": 1,
    "agility": 0,
    "intellect": 0,
    "cunning": 0,
    "willpower": 0,
    "presence": 0,
    "soak": -2,
    "woundThreshold": 0,
    "strainThreshold": 2,
    "meleeDefense": 25,
    "rangedDefense": 0,
    "skills": "15",
    "restricted": true,
    "price": "750000",
    "rarity": "6",
    "sourceURL": "https://star-wars-rpg-ffg.fandom.com/wiki/I-C4a_Combat_Construction_Droid",
    "sourceAPIURL": "https://star-wars-rpg-ffg.fandom.com/api.php?action=parse&page=I-C4a_Combat_Construction_Droid&format=json"
  },
  {
    "category": "STARSHIP & VEHICULAR DROIDS",
    "model": "IG-227 Hailfire Tank",
    "npc": "3",
    "brawn": 3,
    "agility": 0,
    "intellect": 0,
    "cunning": 0,
    "willpower": 0,
    "presence": 0,
    "soak": 2,
    "woundThreshold": 0,
    "strainThreshold": 1,
    "meleeDefense": 6,
    "rangedDefense": 0,
    "skills": "8",
    "restricted": true,
    "price": "25000",
    "rarity": "6",
    "sourceURL": "https://star-wars-rpg-ffg.fandom.com/wiki/IG-227_Hailfire_Tank",
    "sourceAPIURL": "https://star-wars-rpg-ffg.fandom.com/api.php?action=parse&page=IG-227_Hailfire_Tank&format=json"
  },
  {
    "category": "STARSHIP & VEHICULAR DROIDS",
    "model": "NR-N99 Persuader Heavy Droid Tank",
    "npc": "3",
    "brawn": 2,
    "agility": 0,
    "intellect": 0,
    "cunning": 0,
    "willpower": 0,
    "presence": 0,
    "soak": -1,
    "woundThreshold": 0,
    "strainThreshold": 4,
    "meleeDefense": 25,
    "rangedDefense": 0,
    "skills": "18",
    "restricted": true,
    "price": "120000",
    "rarity": "5",
    "sourceURL": "https://star-wars-rpg-ffg.fandom.com/wiki/NR-N99_Persuader_Heavy_Droid_Tank",
    "sourceAPIURL": "https://star-wars-rpg-ffg.fandom.com/api.php?action=parse&page=NR-N99_Persuader_Heavy_Droid_Tank&format=json"
  },
  {
    "category": "STARSHIP & VEHICULAR DROIDS",
    "model": "Q-Signal Messenger Drone (vessel)",
    "npc": "2",
    "brawn": 0,
    "agility": 0,
    "intellect": 0,
    "cunning": 0,
    "willpower": 0,
    "presence": 0,
    "soak": 0,
    "woundThreshold": 0,
    "strainThreshold": 2,
    "meleeDefense": 15,
    "rangedDefense": 0,
    "skills": "10",
    "restricted": false,
    "price": "12000",
    "rarity": "5",
    "sourceURL": "https://star-wars-rpg-ffg.fandom.com/wiki/Q-Signal_Messenger_Drone",
    "sourceAPIURL": "https://star-wars-rpg-ffg.fandom.com/api.php?action=parse&page=Q-Signal_Messenger_Drone&format=json"
  },
  {
    "category": "STARSHIP & VEHICULAR DROIDS",
    "model": "Sentry Droid",
    "npc": "3",
    "brawn": 4,
    "agility": 0,
    "intellect": 0,
    "cunning": 0,
    "willpower": 0,
    "presence": 0,
    "soak": 0,
    "woundThreshold": 0,
    "strainThreshold": 3,
    "meleeDefense": 10,
    "rangedDefense": 0,
    "skills": "12",
    "restricted": false,
    "price": "Unknown",
    "rarity": "",
    "sourceURL": "https://star-wars-rpg-ffg.fandom.com/wiki/Sentry_Droid",
    "sourceAPIURL": "https://star-wars-rpg-ffg.fandom.com/api.php?action=parse&page=Sentry_Droid&format=json"
  },
  {
    "category": "STARSHIP & VEHICULAR DROIDS",
    "model": "Sheathipede-class Shuttle (automated)",
    "npc": "4",
    "brawn": 3,
    "agility": 0,
    "intellect": 0,
    "cunning": 0,
    "willpower": 0,
    "presence": 0,
    "soak": 1,
    "woundThreshold": 1,
    "strainThreshold": 4,
    "meleeDefense": 25,
    "rangedDefense": 0,
    "skills": "15",
    "restricted": false,
    "price": "120000",
    "rarity": "6",
    "sourceURL": "https://star-wars-rpg-ffg.fandom.com/wiki/Sheathipede-class_Shuttle",
    "sourceAPIURL": "https://star-wars-rpg-ffg.fandom.com/api.php?action=parse&page=Sheathipede-class_Shuttle&format=json"
  },
  {
    "category": "STARSHIP & VEHICULAR DROIDS",
    "model": "Vulture-class Droid Starfighter",
    "npc": "3",
    "brawn": 5,
    "agility": 0,
    "intellect": 0,
    "cunning": 0,
    "willpower": 0,
    "presence": 0,
    "soak": 2,
    "woundThreshold": 0,
    "strainThreshold": 2,
    "meleeDefense": 8,
    "rangedDefense": 0,
    "skills": "6",
    "restricted": false,
    "price": "40000",
    "rarity": "5",
    "sourceURL": "https://star-wars-rpg-ffg.fandom.com/wiki/Vulture-class_Droid_Starfighter",
    "sourceAPIURL": "https://star-wars-rpg-ffg.fandom.com/api.php?action=parse&page=Vulture-class_Droid_Starfighter&format=json"
  },
  {
    "category": "STARSHIP & VEHICULAR DROIDS",
    "model": "YQ-400 Monitor-Class System Patrol Ship",
    "npc": "4",
    "brawn": 3,
    "agility": 0,
    "intellect": 0,
    "cunning": 0,
    "willpower": 0,
    "presence": 0,
    "soak": 0,
    "woundThreshold": 1,
    "strainThreshold": 2,
    "meleeDefense": 28,
    "rangedDefense": 0,
    "skills": "30",
    "restricted": false,
    "price": "200000",
    "rarity": "8",
    "sourceURL": "https://star-wars-rpg-ffg.fandom.com/wiki/YQ-400_Monitor-Class_System_Patrol_Ship",
    "sourceAPIURL": "https://star-wars-rpg-ffg.fandom.com/api.php?action=parse&page=YQ-400_Monitor-Class_System_Patrol_Ship&format=json"
  }
]